grains/conf.py
grains/scripts.py
grains/version.py
grains/grains/init.py
grainsv2-11.10.dist-info/METADATA
grainsv2-11.10.dist-info/WHEEL
grainsv2-11.10.dist-info/entry_points.txt
grainsv2-11.10.dist-info/top_level.txt
grainsv2-11.10.dist-info/RECORD
