Metadata-Version: 2.1
Name: grainsv2
Version: 11.10
Summary: System information discovery and asset tracking
Home-page: https://gitlab.com/saltstack/pop/grains
Author: Tyler Johnson
Author-email: tjohnson@saltstack.com
License: UNKNOWN
Platform: UNKNOWN
Classifier: Operating System :: OS Independent
Classifier: Programming Language :: Python
Classifier: Programming Language :: Python :: 3.6
Classifier: Programming Language :: Python :: 3.7
Classifier: Programming Language :: Python :: 3.8
Classifier: Development Status :: 5 - Production/Stable
Requires-Python: >=3.6
Requires-Dist: idem
Requires-Dist: pop (>=14.1)
Requires-Dist: pop-config (>=6.11)
Requires-Dist: rend (>=4.2)
